rigour/__init__.py
rigour/boolean.py
rigour/env.py
rigour/py.typed
rigour/reset.py
rigour/time.py
rigour/units.py
rigour/util.py
rigour/addresses/__init__.py
rigour/addresses/cleaning.py
rigour/addresses/format.py
rigour/addresses/normalize.py
rigour/data/__init__.py
rigour/data/types.py
rigour/data/addresses/__init__.py
rigour/data/addresses/data.py
rigour/data/addresses/formats.yml
rigour/data/langs/__init__.py
rigour/data/langs/iso639.py
rigour/data/names/__init__.py
rigour/data/names/data.py
rigour/data/names/org_types.py
rigour/data/names/persons.txt
rigour/data/territories/__init__.py
rigour/data/territories/data.jsonl
rigour/data/text/__init__.py
rigour/data/text/ordinals.py
rigour/data/text/scripts.py
rigour/ids/__init__.py
rigour/ids/common.py
rigour/ids/imo.py
rigour/ids/npi.py
rigour/ids/ogrn.py
rigour/ids/stdnum_.py
rigour/ids/strict.py
rigour/ids/uei.py
rigour/ids/wikidata.py
rigour/langs/__init__.py
rigour/langs/synonyms.py
rigour/langs/text.py
rigour/langs/util.py
rigour/mime/__init__.py
rigour/mime/filename.py
rigour/mime/mappings.py
rigour/mime/mime.py
rigour/mime/parse.py
rigour/mime/types.py
rigour/names/__init__.py
rigour/names/alignment.py
rigour/names/check.py
rigour/names/name.py
rigour/names/org_types.py
rigour/names/part.py
rigour/names/person.py
rigour/names/pick.py
rigour/names/prefix.py
rigour/names/symbol.py
rigour/names/tag.py
rigour/names/tagging.py
rigour/names/tokenize.py
rigour/territories/__init__.py
rigour/territories/lookup.py
rigour/territories/match.py
rigour/territories/territory.py
rigour/territories/util.py
rigour/text/__init__.py
rigour/text/checksum.py
rigour/text/cleaning.py
rigour/text/dictionary.py
rigour/text/distance.py
rigour/text/numbers.py
rigour/text/phonetics.py
rigour/text/scripts.py
rigour/urls/__init__.py
rigour/urls/cleaning.py
rigour/urls/compare.py
rigour/urls/util.py
rigour-1.6.1.dist-info/METADATA
rigour-1.6.1.dist-info/WHEEL
rigour-1.6.1.dist-info/licenses/LICENSE
rigour-1.6.1.dist-info/RECORD
