Metadata-Version: 2.4
Name: rigour
Version: 1.6.1
Summary: Financial crime domain data validation and normalization library.
Project-URL: Documentation, https://rigour.followthemoney.tech/
Project-URL: Repository, https://github.com/opensanctions/rigour.git
Project-URL: Issues, https://github.com/opensanctions/rigour/issues
Author-email: OpenSanctions <info@opensanctions.org>
License: MIT License
License-File: LICENSE
Classifier: Intended Audience :: Developers
Classifier: License :: OSI Approved :: MIT License
Classifier: Operating System :: OS Independent
Classifier: Programming Language :: Python :: 3.10
Classifier: Programming Language :: Python :: 3.11
Classifier: Programming Language :: Python :: 3.12
Requires-Python: >=3.10
Requires-Dist: ahocorasick-rs<1.1.0,>=0.22.0
Requires-Dist: babel<3.0.0,>=2.9.1
Requires-Dist: banal<1.1.0,>=1.0.6
Requires-Dist: fingerprints<2.0.0,>=1.0.1
Requires-Dist: jellyfish<2.0.0,>=1.0.0
Requires-Dist: jinja2<4.0.0,>=3.1.0
Requires-Dist: normality<4.0.0,>=3.0.1
Requires-Dist: orjson<4.0.0,>=3.0.0
Requires-Dist: pyicu<3.0.0,>=2.0.0
Requires-Dist: python-stdnum<3.0.0,>=2.0
Requires-Dist: pyyaml<7.0.0,>=5.0.0
Requires-Dist: rapidfuzz<4.0.0,>=3.9.0
Provides-Extra: dev
Requires-Dist: black; extra == 'dev'
Requires-Dist: build; extra == 'dev'
Requires-Dist: bump2version; extra == 'dev'
Requires-Dist: coverage>=4.1; extra == 'dev'
Requires-Dist: mypy; extra == 'dev'
Requires-Dist: pip>=10.0.0; extra == 'dev'
Requires-Dist: pytest; extra == 'dev'
Requires-Dist: pytest-cov; extra == 'dev'
Requires-Dist: twine; extra == 'dev'
Requires-Dist: types-pyyaml; extra == 'dev'
Requires-Dist: types-requests; extra == 'dev'
Requires-Dist: types-setuptools; extra == 'dev'
Requires-Dist: wheel>=0.29.0; extra == 'dev'
Provides-Extra: docs
Requires-Dist: cairosvg; extra == 'docs'
Requires-Dist: mkdocs; extra == 'docs'
Requires-Dist: mkdocs-material; extra == 'docs'
Requires-Dist: mkdocstrings[python]; extra == 'docs'
Requires-Dist: pillow; extra == 'docs'
